RPistepper/__init__.py
RPistepper/gui.py
RPistepper/shell.py
RPistepper-0.3a1.data/scripts/rpistepper
RPistepper-0.3a1.dist-info/LICENSE.md
RPistepper-0.3a1.dist-info/METADATA
RPistepper-0.3a1.dist-info/WHEEL
RPistepper-0.3a1.dist-info/top_level.txt
RPistepper-0.3a1.dist-info/RECORD
