Metadata-Version: 1.1
Name: RPistepper
Version: 0.3a1
Summary: RPistepper is a library control stepper motors using a Raspberry Pi and a transistor array
Home-page: https://github.com/luxedo/RPistepper
Author: Luiz Eduardo Nishino Gomes do Amaral
Author-email: luizamaral306@gmail.com
License: GPL3
Keywords: RPi ULN2803A stepper motor
Platform: UNKNOWN
Classifier: Development Status :: 3 - Alpha
Classifier: Intended Audience :: Developers
Classifier: Topic :: System :: Hardware
Classifier: Topic :: Software Development :: Libraries :: Python Modules
Classifier: License :: OSI Approved :: GNU General Public License v3 or later (GPLv3+)
Classifier: Programming Language :: Python :: 2
Classifier: Programming Language :: Python :: 2.6
Classifier: Programming Language :: Python :: 2.7
Classifier: Programming Language :: Python :: 3
Classifier: Programming Language :: Python :: 3.2
Classifier: Programming Language :: Python :: 3.3
Classifier: Programming Language :: Python :: 3.4
